PerceptronX/Perceptron.py
PerceptronX/__init__.py
neuroml-0.1.0.dist-info/licenses/LICENSE.txt
neuroml-0.1.0.dist-info/METADATA
neuroml-0.1.0.dist-info/WHEEL
neuroml-0.1.0.dist-info/top_level.txt
neuroml-0.1.0.dist-info/RECORD
