Metadata-Version: 2.4
Name: NeuroML
Version: 0.1.0
Summary: Perceptron implementation for linear, binary, and multi-class tasks
Home-page: https://github.com/ml-beginner-learner/PerceptronLib
Author: Ajay Soni
Classifier: Programming Language :: Python :: 3
Classifier: License :: OSI Approved :: MIT License
Classifier: Operating System :: OS Independent
Requires-Python: >=3.6
License-File: LICENSE.txt
Requires-Dist: numpy
Requires-Dist: pandas
Requires-Dist: scikit-learn
Dynamic: author
Dynamic: classifier
Dynamic: description
Dynamic: description-content-type
Dynamic: home-page
Dynamic: license-file
Dynamic: requires-dist
Dynamic: requires-python
Dynamic: summary
